[
  {
    "timestamp": "2026-04-03 14:07:33",
    "source": "auth",
    "event_type": "login",
    "status": "failed",
    "ip": "192.168.1.45",
    "user": "admin",
    "technique": "Brute Force (T1110)"
  },
  {
    "timestamp": "2026-04-03 14:12:09",
    "source": "auth",
    "event_type": "login",
    "status": "success",
    "ip": "192.168.1.45",
    "user": "admin",
    "technique": "Valid Accounts (T1078)"
  },
  {
    "timestamp": "2026-04-03 14:25:10",
    "source": "auth",
    "event_type": "login",
    "status": "success",
    "ip": "172.16.0.12",
    "user": "guest_user",
    "technique": "Valid Accounts (T1078)"
  }
]